{
  "hash": "eac2b996",
  "configHash": "f92e065a",
  "lockfileHash": "f765b6f9",
  "browserHash": "43238f66",
  "optimized": {
    "vue": {
      "src": "../../../../node_modules/vue/dist/vue.runtime.esm-bundler.js",
      "file": "vue.js",
      "fileHash": "ec3c5e27",
      "needsInterop": false
    },
    "vitepress > @vue/devtools-api": {
      "src": "../../../../node_modules/@vue/devtools-api/dist/index.js",
      "file": "vitepress___@vue_devtools-api.js",
      "fileHash": "2cd791a6",
      "needsInterop": false
    },
    "vitepress > @vueuse/core": {
      "src": "../../../../node_modules/@vueuse/core/index.mjs",
      "file": "vitepress___@vueuse_core.js",
      "fileHash": "753c1ee3",
      "needsInterop": false
    },
    "element-plus": {
      "src": "../../../../node_modules/element-plus/es/index.mjs",
      "file": "element-plus.js",
      "fileHash": "f6521a65",
      "needsInterop": false
    },
    "echarts/core": {
      "src": "../../../../node_modules/echarts/core.js",
      "file": "echarts_core.js",
      "fileHash": "2d7f6559",
      "needsInterop": false
    },
    "echarts/components": {
      "src": "../../../../node_modules/echarts/components.js",
      "file": "echarts_components.js",
      "fileHash": "f680abc8",
      "needsInterop": false
    },
    "echarts/charts": {
      "src": "../../../../node_modules/echarts/charts.js",
      "file": "echarts_charts.js",
      "fileHash": "30962521",
      "needsInterop": false
    },
    "echarts/features": {
      "src": "../../../../node_modules/echarts/features.js",
      "file": "echarts_features.js",
      "fileHash": "ac1d11d1",
      "needsInterop": false
    },
    "echarts/renderers": {
      "src": "../../../../node_modules/echarts/renderers.js",
      "file": "echarts_renderers.js",
      "fileHash": "1a139860",
      "needsInterop": false
    },
    "vue-draggable-plus": {
      "src": "../../../../node_modules/vue-draggable-plus/dist/vue-draggable-plus.js",
      "file": "vue-draggable-plus.js",
      "fileHash": "d09790db",
      "needsInterop": false
    },
    "vue-demi": {
      "src": "../../../../node_modules/vitepress/lib/vue-demi.mjs",
      "file": "vue-demi.js",
      "fileHash": "9da71d61",
      "needsInterop": false
    }
  },
  "chunks": {
    "chunk-ZDT2FX2F": {
      "file": "chunk-ZDT2FX2F.js"
    },
    "chunk-RKA2G3BJ": {
      "file": "chunk-RKA2G3BJ.js"
    },
    "chunk-7VSZJW2V": {
      "file": "chunk-7VSZJW2V.js"
    },
    "chunk-ZVJ6ZVDY": {
      "file": "chunk-ZVJ6ZVDY.js"
    },
    "chunk-K2WVBYSR": {
      "file": "chunk-K2WVBYSR.js"
    },
    "chunk-XLIOIY5X": {
      "file": "chunk-XLIOIY5X.js"
    },
    "chunk-YFIF3WP3": {
      "file": "chunk-YFIF3WP3.js"
    },
    "chunk-LAUGXQ7V": {
      "file": "chunk-LAUGXQ7V.js"
    },
    "chunk-M3HCBZP4": {
      "file": "chunk-M3HCBZP4.js"
    },
    "chunk-GHHEI547": {
      "file": "chunk-GHHEI547.js"
    },
    "chunk-ZS7NZCD4": {
      "file": "chunk-ZS7NZCD4.js"
    }
  }
}